{
  "uid" : "686ed3a2a93b7f13",
  "name" : "test_converter[param_test11]",
  "title" : "Test converter [param_test11]",
  "time" : {
    "start" : 1484254196289,
    "stop" : 1484254197983,
    "duration" : 1694
  },
  "summary" : {
    "attachments" : 0,
    "steps" : 3
  },
  "failure" : null,
  "description" : null,
  "severity" : "NORMAL",
  "status" : "PASSED",
  "suite" : {
    "uid" : "cc738abc920faf34",
    "name" : "test_suite.test_converter",
    "title" : "Test converter"
  },
  "steps" : [ {
    "name" : "Ввод новых данных в поле \"Сумма\"",
    "title" : "Ввод новых данных в поле \"Сумма\"",
    "time" : {
      "start" : 1484254196289,
      "stop" : 1484254197983,
      "duration" : 1694
    },
    "summary" : {
      "attachments" : 0,
      "steps" : 1
    },
    "status" : "PASSED",
    "attachments" : [ ],
    "steps" : [ {
      "name" : "Вывод результата",
      "title" : "Вывод результата",
      "time" : {
        "start" : 1484254196757,
        "stop" : 1484254197983,
        "duration" : 1226
      },
      "summary" : {
        "attachments" : 0,
        "steps" : 0
      },
      "status" : "PASSED",
      "attachments" : [ ],
      "steps" : [ ]
    } ]
  }, {
    "name" : "Проверка результата",
    "title" : "Проверка результата",
    "time" : {
      "start" : 1484254197983,
      "stop" : 1484254197983,
      "duration" : 0
    },
    "summary" : {
      "attachments" : 0,
      "steps" : 0
    },
    "status" : "PASSED",
    "attachments" : [ ],
    "steps" : [ ]
  } ],
  "attachments" : [ ],
  "issues" : [ ],
  "testIds" : [ ],
  "labels" : [ {
    "name" : "feature",
    "value" : "Калькулятор иностранных валют. CRUD-тест: поле ввода суммы"
  }, {
    "name" : "host",
    "value" : "DESKTOP-NA3S6T6"
  }, {
    "name" : "suite-title",
    "value" : null
  }, {
    "name" : "severity",
    "value" : "normal"
  }, {
    "name" : "suite-name",
    "value" : "test_suite.test_converter"
  }, {
    "name" : "thread",
    "value" : "7728-MainThread"
  }, {
    "name" : "story",
    "value" : "Ввод различных параметров и проверка результата"
  } ],
  "parameters" : [ ]
}