{
  "uid" : "cd4f8deed0661258",
  "name" : "test_from_currency[param_test4]",
  "title" : "Test from currency [param_test4]",
  "time" : {
    "start" : 1484256178984,
    "stop" : 1484256179355,
    "duration" : 371
  },
  "summary" : {
    "attachments" : 0,
    "steps" : 2
  },
  "failure" : null,
  "description" : null,
  "severity" : "NORMAL",
  "status" : "PASSED",
  "suite" : {
    "uid" : "20c35108239dd5c4",
    "name" : "test_suite.test_from_currency",
    "title" : "Test from currency"
  },
  "steps" : [ {
    "name" : "Выбор валюты из списка",
    "title" : "Выбор валюты из списка",
    "time" : {
      "start" : 1484256179134,
      "stop" : 1484256179354,
      "duration" : 220
    },
    "summary" : {
      "attachments" : 0,
      "steps" : 0
    },
    "status" : "PASSED",
    "attachments" : [ ],
    "steps" : [ ]
  }, {
    "name" : "Проверка результата",
    "title" : "Проверка результата",
    "time" : {
      "start" : 1484256179354,
      "stop" : 1484256179355,
      "duration" : 1
    },
    "summary" : {
      "attachments" : 0,
      "steps" : 0
    },
    "status" : "PASSED",
    "attachments" : [ ],
    "steps" : [ ]
  } ],
  "attachments" : [ ],
  "issues" : [ ],
  "testIds" : [ ],
  "labels" : [ {
    "name" : "suite-name",
    "value" : "test_suite.test_from_currency"
  }, {
    "name" : "feature",
    "value" : "CRUD-тест: выбор валюты"
  }, {
    "name" : "thread",
    "value" : "7312-MainThread"
  }, {
    "name" : "host",
    "value" : "DESKTOP-NA3S6T6"
  }, {
    "name" : "suite-title",
    "value" : null
  }, {
    "name" : "severity",
    "value" : "normal"
  }, {
    "name" : "story",
    "value" : "Выбор валюты, из которой конвертируем, проверка списка"
  } ],
  "parameters" : [ ]
}